{"res":{"3":{"x":0,"y":0,"w":160,"h":212},"0":{"x":0,"y":212,"w":176,"h":168},"1":{"x":160,"y":0,"w":153,"h":202},"2":{"x":176,"y":202,"w":153,"h":201},"5":{"x":313,"y":0,"w":179,"h":151},"4":{"x":329,"y":151,"w":170,"h":171}},"mc":{"1":{"frameRate":10,"frames":[{"res":"0","x":-101,"y":-146},{"res":"1","x":-89,"y":-182},{"res":"2","x":-89,"y":-181},{"res":"3","x":-94,"y":-190},{"res":"4","x":-75,"y":-148},{"res":"5","x":-68,"y":-114},{"res":"5","x":-68,"y":-114},{"res":"5","x":-68,"y":-114},{"res":"5","x":-68,"y":-114},{"res":"5","x":-68,"y":-114}]}}}