{"res":{"3":{"x":0,"y":0,"w":97,"h":91},"1":{"x":0,"y":91,"w":86,"h":89},"4":{"x":0,"y":180,"w":106,"h":54},"2":{"x":86,"y":91,"w":75,"h":70},"6":{"x":106,"y":161,"w":69,"h":73},"0":{"x":97,"y":0,"w":61,"h":57},"5":{"x":97,"y":57,"w":95,"h":20},"7":{"x":158,"y":0,"w":45,"h":52}},"mc":{"1":{"frameRate":9,"frames":[{"res":"0","x":-36,"y":-83},{"res":"1","x":-28,"y":-116},{"res":"2","x":-54,"y":-112},{"res":"3","x":-56,"y":-117},{"res":"4","x":-60,"y":-118},{"res":"5","x":-58,"y":-100},{"res":"6","x":-51,"y":-121},{"res":"7","x":8,"y":-63},{"res":"7","x":8,"y":-63}]}}}