{"res":{"7":{"x":0,"y":0,"w":115,"h":12},"6":{"x":115,"y":0,"w":115,"h":11},"2":{"x":115,"y":11,"w":104,"h":37},"3":{"x":0,"y":12,"w":94,"h":54},"1":{"x":94,"y":48,"w":93,"h":54},"5":{"x":0,"y":66,"w":91,"h":67},"4":{"x":187,"y":48,"w":62,"h":79},"0":{"x":91,"y":102,"w":89,"h":34}},"mc":{"1":{"frameRate":15,"frames":[{"res":"0","x":-43,"y":-55},{"res":"1","x":-45,"y":-68},{"res":"2","x":-35,"y":-105},{"res":"3","x":-40,"y":-220},{"res":"4","x":-6,"y":-242},{"res":"5","x":11,"y":-171},{"res":"5","x":11,"y":-171},{"res":"5","x":11,"y":-171},{"res":"5","x":11,"y":-171},{"res":"5","x":11,"y":-171},{"res":"5","x":11,"y":-171},{"res":"5","x":11,"y":-171},{"res":"5","x":11,"y":-171},{"res":"6","x":-6,"y":-129},{"res":"7","x":-6,"y":-81}]}}}