{"res":{"10":{"x":0,"y":0,"w":159,"h":209},"7":{"x":0,"y":209,"w":166,"h":185},"2":{"x":159,"y":0,"w":165,"h":183},"11":{"x":0,"y":394,"w":152,"h":193},"8":{"x":0,"y":587,"w":171,"h":145},"0":{"x":152,"y":394,"w":159,"h":180},"12":{"x":171,"y":574,"w":174,"h":164},"15":{"x":166,"y":183,"w":170,"h":167},"3":{"x":324,"y":0,"w":156,"h":181},"5":{"x":311,"y":350,"w":176,"h":159},"6":{"x":336,"y":181,"w":169,"h":165},"13":{"x":480,"y":0,"w":166,"h":164},"4":{"x":345,"y":509,"w":157,"h":153},"14":{"x":487,"y":346,"w":134,"h":157},"1":{"x":505,"y":164,"w":138,"h":174},"9":{"x":502,"y":503,"w":130,"h":184}},"mc":{"1":{"frameRate":25,"frames":[{"res":"0","x":-77,"y":-157},{"res":"0","x":-77,"y":-157},{"res":"0","x":-77,"y":-157},{"res":"1","x":-55,"y":-162},{"res":"2","x":-106,"y":-162},{"res":"3","x":-108,"y":-169},{"res":"4","x":-110,"y":-171},{"res":"5","x":-96,"y":-179},{"res":"6","x":-102,"y":-146},{"res":"2","x":-106,"y":-162},{"res":"3","x":-108,"y":-169},{"res":"4","x":-110,"y":-171},{"res":"5","x":-96,"y":-179},{"res":"6","x":-102,"y":-146},{"res":"7","x":-90,"y":-168},{"res":"8","x":-94,"y":-127},{"res":"9","x":-78,"y":-170},{"res":"10","x":-82,"y":-199},{"res":"11","x":-85,"y":-212},{"res":"12","x":-86,"y":-219},{"res":"13","x":-84,"y":-249},{"res":"14","x":-75,"y":-223},{"res":"15","x":-97,"y":-145},{"res":"15","x":-97,"y":-145},{"res":"15","x":-97,"y":-145}]}}}