{"res":{"2":{"x":0,"y":0,"w":207,"h":35},"1":{"x":0,"y":35,"w":124,"h":57},"0":{"x":124,"y":35,"w":119,"h":55}},"mc":{"1":{"frameRate":1,"frames":[{"res":"0","x":-41,"y":-79}]},"2":{"frameRate":1,"frames":[{"res":"1","x":-19,"y":-107}]},"3":{"frameRate":3,"frames":[{"res":"0","x":-41,"y":-79},{"res":"1","x":-19,"y":-107},{"res":"2","x":-76,"y":-26}]},"4":{"frameRate":1,"frames":[{"res":"2","x":-76,"y":-26}]},"5":{"frameRate":2,"frames":[{"res":"1","x":-19,"y":-107},{"res":"2","x":-76,"y":-26}]}}}